reltools.py
reltools-0.9.4.dist-info/LICENSE
reltools-0.9.4.dist-info/WHEEL
reltools-0.9.4.dist-info/METADATA
reltools-0.9.4.dist-info/RECORD
