Metadata-Version: 2.1
Name: reltools
Version: 0.9.4
Summary: Relation tools for Python.
Home-page: https://github.com/ymoch/reltools
License: MIT
Author: ymoch
Author-email: ymoch.dev@gmail.com
Requires-Python: >=3.5,<4.0
Classifier: License :: OSI Approved :: MIT License
Classifier: Programming Language :: Python :: 3
Classifier: Programming Language :: Python :: 3.5
Classifier: Programming Language :: Python :: 3.6
Classifier: Programming Language :: Python :: 3.7
Requires-Dist: more-itertools (>=7.2,<8.0)
Project-URL: Repository, https://github.com/ymoch/reltools
